{
  "decoder": {
    "offset": {
      "hold": 0.009,
      "median": 1,
      "merge_gap": 0,
      "min_off": 1,
      "min_on": 1,
      "open": 0.015
    },
    "onset": {
      "hold": 0.010799999999999999,
      "median": 1,
      "merge_gap": 0,
      "min_off": 1,
      "min_on": 1,
      "open": 0.018
    }
  },
  "method": "threshold_sweep",
  "metrics": {
    "ev_f1_mean": 0.06468632440671944,
    "offset_event_f1": 0.05848418297853943,
    "onset_event_f1": 0.07088846583489945
  },
  "split": "valid",
  "sweep": {
    "delta": 0.005,
    "max_prob": 0.12,
    "min_prob": 0.001,
    "per_head": {
      "offset": {
        "center": 0.01,
        "results": [
          {
            "clips": 9,
            "f1": 0.03656647004695175,
            "fn": 0,
            "fp": 37308,
            "hold": 0.0006,
            "precision": 0.018623737373732477,
            "recall": 0.9999999999858757,
            "threshold": 0.001,
            "tp": 708
          },
          {
            "clips": 9,
            "f1": 0.030543148905074143,
            "fn": 284,
            "fp": 26632,
            "hold": 0.003,
            "precision": 0.015671200473087052,
            "recall": 0.5988700564887165,
            "threshold": 0.005,
            "tp": 424
          },
          {
            "clips": 9,
            "f1": 0.05066666495675881,
            "fn": 518,
            "fp": 6602,
            "hold": 0.006,
            "precision": 0.02797408716132513,
            "recall": 0.2683615819171135,
            "threshold": 0.01,
            "tp": 190
          },
          {
            "clips": 9,
            "f1": 0.05848418297853943,
            "fn": 561,
            "fp": 4172,
            "hold": 0.009,
            "precision": 0.03403565640186609,
            "recall": 0.2076271186411352,
            "threshold": 0.015,
            "tp": 147
          },
          {
            "clips": 9,
            "f1": 0.05715743516126038,
            "fn": 596,
            "fp": 3099,
            "hold": 0.012,
            "precision": 0.03488009965731897,
            "recall": 0.15819209039324586,
            "threshold": 0.02,
            "tp": 112
          },
          {
            "clips": 9,
            "f1": 0.051986850562971094,
            "fn": 621,
            "fp": 2552,
            "hold": 0.015,
            "precision": 0.03296703296690805,
            "recall": 0.12288135593046777,
            "threshold": 0.025,
            "tp": 87
          },
          {
            "clips": 9,
            "f1": 0.05196679518473114,
            "fn": 636,
            "fp": 1991,
            "hold": 0.018,
            "precision": 0.03490063015009743,
            "recall": 0.10169491525280092,
            "threshold": 0.03,
            "tp": 72
          },
          {
            "clips": 9,
            "f1": 0.050765507606035334,
            "fn": 645,
            "fp": 1711,
            "hold": 0.021,
            "precision": 0.03551296505053262,
            "recall": 0.0889830508462008,
            "threshold": 0.035,
            "tp": 63
          },
          {
            "clips": 9,
            "f1": 0.05456907327013297,
            "fn": 645,
            "fp": 1538,
            "hold": 0.024,
            "precision": 0.03935040599600656,
            "recall": 0.0889830508462008,
            "threshold": 0.04,
            "tp": 63
          },
          {
            "clips": 9,
            "f1": 0.05367231193923133,
            "fn": 651,
            "fp": 1359,
            "hold": 0.027,
            "precision": 0.04025423728785132,
            "recall": 0.08050847457513406,
            "threshold": 0.045,
            "tp": 57
          },
          {
            "clips": 9,
            "f1": 0.05566801159534902,
            "fn": 653,
            "fp": 1213,
            "hold": 0.03,
            "precision": 0.04337539432142449,
            "recall": 0.07768361581811181,
            "threshold": 0.05,
            "tp": 55
          },
          {
            "clips": 9,
            "f1": 0.046713737797191096,
            "fn": 665,
            "fp": 1090,
            "hold": 0.033,
            "precision": 0.03795233892287774,
            "recall": 0.060734463275978326,
            "threshold": 0.055,
            "tp": 43
          },
          {
            "clips": 9,
            "f1": 0.0496535748425379,
            "fn": 665,
            "fp": 981,
            "hold": 0.036,
            "precision": 0.041992187499589925,
            "recall": 0.060734463275978326,
            "threshold": 0.06,
            "tp": 43
          },
          {
            "clips": 9,
            "f1": 0.050663445045595834,
            "fn": 666,
            "fp": 908,
            "hold": 0.039,
            "precision": 0.0442105263153241,
            "recall": 0.0593220338974672,
            "threshold": 0.065,
            "tp": 42
          },
          {
            "clips": 9,
            "f1": 0.048994969934866406,
            "fn": 669,
            "fp": 845,
            "hold": 0.042,
            "precision": 0.04411764705832446,
            "recall": 0.05508474576193383,
            "threshold": 0.07,
            "tp": 39
          }
        ],
        "source": "training.metrics",
        "values": [
          0.001,
          0.005,
          0.01,
          0.015,
          0.02,
          0.025,
          0.03,
          0.035,
          0.04,
          0.045,
          0.05,
          0.055,
          0.06,
          0.065,
          0.07
        ]
      },
      "onset": {
        "center": 0.008,
        "results": [
          {
            "clips": 9,
            "f1": 0.03965450521913499,
            "fn": 0,
            "fp": 37247,
            "hold": 0.0006,
            "precision": 0.020228324915819596,
            "recall": 0.9999999999869961,
            "threshold": 0.001,
            "tp": 769
          },
          {
            "clips": 9,
            "f1": 0.03979507309369769,
            "fn": 0,
            "fp": 37110,
            "hold": 0.0018,
            "precision": 0.020301486311671297,
            "recall": 0.9999999999869961,
            "threshold": 0.003,
            "tp": 769
          },
          {
            "clips": 9,
            "f1": 0.049577770425219415,
            "fn": 496,
            "fp": 9971,
            "hold": 0.0048,
            "precision": 0.026649746192867384,
            "recall": 0.3550065019459687,
            "threshold": 0.008,
            "tp": 273
          },
          {
            "clips": 9,
            "f1": 0.06220999942451864,
            "fn": 588,
            "fp": 4869,
            "hold": 0.0078,
            "precision": 0.03584158415834487,
            "recall": 0.23537061118029426,
            "threshold": 0.013,
            "tp": 181
          },
          {
            "clips": 9,
            "f1": 0.07088846583489945,
            "fn": 619,
            "fp": 3313,
            "hold": 0.010799999999999999,
            "precision": 0.04331504475875451,
            "recall": 0.19505851755273004,
            "threshold": 0.018,
            "tp": 150
          },
          {
            "clips": 9,
            "f1": 0.07048710258093957,
            "fn": 646,
            "fp": 2598,
            "hold": 0.0138,
            "precision": 0.04520396912883056,
            "recall": 0.15994798439323865,
            "threshold": 0.023,
            "tp": 123
          },
          {
            "clips": 9,
            "f1": 0.0635130626963751,
            "fn": 673,
            "fp": 2158,
            "hold": 0.0168,
            "precision": 0.042590949423058605,
            "recall": 0.12483745123374723,
            "threshold": 0.028,
            "tp": 96
          },
          {
            "clips": 9,
            "f1": 0.053403531051872226,
            "fn": 698,
            "fp": 1819,
            "hold": 0.0198,
            "precision": 0.0375661375659388,
            "recall": 0.09232769830829222,
            "threshold": 0.033,
            "tp": 71
          },
          {
            "clips": 9,
            "f1": 0.05278591938575293,
            "fn": 706,
            "fp": 1555,
            "hold": 0.022799999999999997,
            "precision": 0.03893695920865923,
            "recall": 0.08192457737214662,
            "threshold": 0.038,
            "tp": 63
          },
          {
            "clips": 9,
            "f1": 0.0552584625175993,
            "fn": 707,
            "fp": 1413,
            "hold": 0.025799999999999997,
            "precision": 0.042033898304799776,
            "recall": 0.08062418725512842,
            "threshold": 0.043,
            "tp": 62
          },
          {
            "clips": 9,
            "f1": 0.054105358439590544,
            "fn": 712,
            "fp": 1281,
            "hold": 0.0288,
            "precision": 0.04260089686066816,
            "recall": 0.07412223667003742,
            "threshold": 0.048,
            "tp": 57
          },
          {
            "clips": 9,
            "f1": 0.04778496291994187,
            "fn": 721,
            "fp": 1192,
            "hold": 0.031799999999999995,
            "precision": 0.038709677419042667,
            "recall": 0.062418725616873616,
            "threshold": 0.053,
            "tp": 48
          },
          {
            "clips": 9,
            "f1": 0.04651162304792872,
            "fn": 726,
            "fp": 1037,
            "hold": 0.0348,
            "precision": 0.03981481481444616,
            "recall": 0.05591677503178261,
            "threshold": 0.058,
            "tp": 43
          },
          {
            "clips": 9,
            "f1": 0.03583426161336404,
            "fn": 737,
            "fp": 985,
            "hold": 0.0378,
            "precision": 0.03146509341168668,
            "recall": 0.041612483744582415,
            "threshold": 0.063,
            "tp": 32
          },
          {
            "clips": 9,
            "f1": 0.03561171247135991,
            "fn": 738,
            "fp": 941,
            "hold": 0.0408,
            "precision": 0.03189300411489822,
            "recall": 0.04031209362756421,
            "threshold": 0.068,
            "tp": 31
          }
        ],
        "source": "training.metrics",
        "values": [
          0.001,
          0.003,
          0.008,
          0.013,
          0.018,
          0.023,
          0.028,
          0.033,
          0.038,
          0.043,
          0.048,
          0.053,
          0.058,
          0.063,
          0.068
        ]
      }
    },
    "steps": 25
  },
  "thresholds": {
    "offset": 0.015,
    "onset": 0.018
  }
}