{
  "decoder": {
    "offset": {
      "hold": 0.042,
      "median": 1,
      "merge_gap": 0,
      "min_off": 1,
      "min_on": 1,
      "open": 0.07
    },
    "onset": {
      "hold": 0.0408,
      "median": 1,
      "merge_gap": 0,
      "min_off": 1,
      "min_on": 1,
      "open": 0.068
    }
  },
  "method": "threshold_sweep",
  "metrics": {
    "ev_f1_mean": 0.07523188220640578,
    "offset_event_f1": 0.07658748943191108,
    "onset_event_f1": 0.07387627498090049
  },
  "split": "valid",
  "sweep": {
    "delta": 0.005,
    "max_prob": 0.12,
    "min_prob": 0.001,
    "per_head": {
      "offset": {
        "center": 0.01,
        "results": [
          {
            "clips": 9,
            "f1": 0.03669439441548272,
            "fn": 0,
            "fp": 37173,
            "hold": 0.0006,
            "precision": 0.018690108497658803,
            "recall": 0.9999999999858757,
            "threshold": 0.001,
            "tp": 708
          },
          {
            "clips": 9,
            "f1": 0.028028630215223616,
            "fn": 289,
            "fp": 28771,
            "hold": 0.003,
            "precision": 0.014354230900988573,
            "recall": 0.5918079095961609,
            "threshold": 0.005,
            "tp": 419
          },
          {
            "clips": 9,
            "f1": 0.062164054260729094,
            "fn": 575,
            "fp": 3438,
            "hold": 0.006,
            "precision": 0.037244469336216064,
            "recall": 0.18785310734197946,
            "threshold": 0.01,
            "tp": 133
          },
          {
            "clips": 9,
            "f1": 0.07495853703603174,
            "fn": 595,
            "fp": 2194,
            "hold": 0.009,
            "precision": 0.04898136107477685,
            "recall": 0.159604519771757,
            "threshold": 0.015,
            "tp": 113
          },
          {
            "clips": 9,
            "f1": 0.06707316679087993,
            "fn": 620,
            "fp": 1828,
            "hold": 0.012,
            "precision": 0.04592901878890434,
            "recall": 0.1242937853089789,
            "threshold": 0.02,
            "tp": 88
          },
          {
            "clips": 9,
            "f1": 0.06623586021310911,
            "fn": 626,
            "fp": 1686,
            "hold": 0.015,
            "precision": 0.046380090497475226,
            "recall": 0.11581920903791215,
            "threshold": 0.025,
            "tp": 82
          },
          {
            "clips": 9,
            "f1": 0.06728342727270825,
            "fn": 628,
            "fp": 1590,
            "hold": 0.018,
            "precision": 0.047904191616479616,
            "recall": 0.11299435028088992,
            "threshold": 0.03,
            "tp": 80
          },
          {
            "clips": 9,
            "f1": 0.06791171056615221,
            "fn": 628,
            "fp": 1568,
            "hold": 0.021,
            "precision": 0.04854368932009379,
            "recall": 0.11299435028088992,
            "threshold": 0.035,
            "tp": 80
          },
          {
            "clips": 9,
            "f1": 0.06980802365298248,
            "fn": 628,
            "fp": 1504,
            "hold": 0.024,
            "precision": 0.05050505050473166,
            "recall": 0.11299435028088992,
            "threshold": 0.04,
            "tp": 80
          },
          {
            "clips": 9,
            "f1": 0.06948108630046848,
            "fn": 629,
            "fp": 1487,
            "hold": 0.027,
            "precision": 0.050446998722538654,
            "recall": 0.11158192090237878,
            "threshold": 0.045,
            "tp": 79
          },
          {
            "clips": 9,
            "f1": 0.0710112316154266,
            "fn": 629,
            "fp": 1438,
            "hold": 0.03,
            "precision": 0.05207646671026977,
            "recall": 0.11158192090237878,
            "threshold": 0.05,
            "tp": 79
          },
          {
            "clips": 9,
            "f1": 0.0736596692365117,
            "fn": 629,
            "fp": 1358,
            "hold": 0.033,
            "precision": 0.054975643701774705,
            "recall": 0.11158192090237878,
            "threshold": 0.055,
            "tp": 79
          },
          {
            "clips": 9,
            "f1": 0.0741088135744875,
            "fn": 629,
            "fp": 1345,
            "hold": 0.036,
            "precision": 0.05547752808949805,
            "recall": 0.11158192090237878,
            "threshold": 0.06,
            "tp": 79
          },
          {
            "clips": 9,
            "f1": 0.07534572752468582,
            "fn": 629,
            "fp": 1310,
            "hold": 0.039,
            "precision": 0.056875449963593415,
            "recall": 0.11158192090237878,
            "threshold": 0.065,
            "tp": 79
          },
          {
            "clips": 9,
            "f1": 0.07658748943191108,
            "fn": 629,
            "fp": 1276,
            "hold": 0.042,
            "precision": 0.058302583025399986,
            "recall": 0.11158192090237878,
            "threshold": 0.07,
            "tp": 79
          }
        ],
        "source": "training.metrics",
        "values": [
          0.001,
          0.005,
          0.01,
          0.015,
          0.02,
          0.025,
          0.03,
          0.035,
          0.04,
          0.045,
          0.05,
          0.055,
          0.06,
          0.065,
          0.07
        ]
      },
      "onset": {
        "center": 0.008,
        "results": [
          {
            "clips": 9,
            "f1": 0.03986521474665026,
            "fn": 0,
            "fp": 37042,
            "hold": 0.0006,
            "precision": 0.020337996879209667,
            "recall": 0.9999999999869961,
            "threshold": 0.001,
            "tp": 769
          },
          {
            "clips": 9,
            "f1": 0.039948051556529925,
            "fn": 0,
            "fp": 36962,
            "hold": 0.0018,
            "precision": 0.02038111897378273,
            "recall": 0.9999999999869961,
            "threshold": 0.003,
            "tp": 769
          },
          {
            "clips": 9,
            "f1": 0.04877360956952913,
            "fn": 596,
            "fp": 6152,
            "hold": 0.0048,
            "precision": 0.02735177865608324,
            "recall": 0.22496749024414867,
            "threshold": 0.008,
            "tp": 173
          },
          {
            "clips": 9,
            "f1": 0.06622162557458275,
            "fn": 645,
            "fp": 2852,
            "hold": 0.0078,
            "precision": 0.04166666666652666,
            "recall": 0.16124837451025684,
            "threshold": 0.013,
            "tp": 124
          },
          {
            "clips": 9,
            "f1": 0.05634758609421065,
            "fn": 686,
            "fp": 2094,
            "hold": 0.010799999999999999,
            "precision": 0.03812586127681155,
            "recall": 0.10793237971251063,
            "threshold": 0.018,
            "tp": 83
          },
          {
            "clips": 9,
            "f1": 0.061367833268439295,
            "fn": 686,
            "fp": 1853,
            "hold": 0.0138,
            "precision": 0.042871900826224836,
            "recall": 0.10793237971251063,
            "threshold": 0.023,
            "tp": 83
          },
          {
            "clips": 9,
            "f1": 0.06406792326648054,
            "fn": 686,
            "fp": 1739,
            "hold": 0.0168,
            "precision": 0.04555433589437127,
            "recall": 0.10793237971251063,
            "threshold": 0.028,
            "tp": 83
          },
          {
            "clips": 9,
            "f1": 0.06540582713898652,
            "fn": 686,
            "fp": 1686,
            "hold": 0.0198,
            "precision": 0.04691916336886988,
            "recall": 0.10793237971251063,
            "threshold": 0.033,
            "tp": 83
          },
          {
            "clips": 9,
            "f1": 0.06775509773309482,
            "fn": 686,
            "fp": 1598,
            "hold": 0.022799999999999997,
            "precision": 0.04937537180220479,
            "recall": 0.10793237971251063,
            "threshold": 0.038,
            "tp": 83
          },
          {
            "clips": 9,
            "f1": 0.06887966370381048,
            "fn": 686,
            "fp": 1558,
            "hold": 0.025799999999999997,
            "precision": 0.050578915295243276,
            "recall": 0.10793237971251063,
            "threshold": 0.043,
            "tp": 83
          },
          {
            "clips": 9,
            "f1": 0.07007175585103163,
            "fn": 686,
            "fp": 1517,
            "hold": 0.0288,
            "precision": 0.051874999999675785,
            "recall": 0.10793237971251063,
            "threshold": 0.048,
            "tp": 83
          },
          {
            "clips": 9,
            "f1": 0.07118352902670827,
            "fn": 686,
            "fp": 1480,
            "hold": 0.031799999999999995,
            "precision": 0.053103007037408174,
            "recall": 0.10793237971251063,
            "threshold": 0.053,
            "tp": 83
          },
          {
            "clips": 9,
            "f1": 0.07315997788940624,
            "fn": 686,
            "fp": 1417,
            "hold": 0.0348,
            "precision": 0.055333333332964446,
            "recall": 0.10793237971251063,
            "threshold": 0.058,
            "tp": 83
          },
          {
            "clips": 9,
            "f1": 0.07335395043962842,
            "fn": 686,
            "fp": 1411,
            "hold": 0.0378,
            "precision": 0.055555555555183704,
            "recall": 0.10793237971251063,
            "threshold": 0.063,
            "tp": 83
          },
          {
            "clips": 9,
            "f1": 0.07387627498090049,
            "fn": 686,
            "fp": 1395,
            "hold": 0.0408,
            "precision": 0.056156968876480674,
            "recall": 0.10793237971251063,
            "threshold": 0.068,
            "tp": 83
          }
        ],
        "source": "training.metrics",
        "values": [
          0.001,
          0.003,
          0.008,
          0.013,
          0.018,
          0.023,
          0.028,
          0.033,
          0.038,
          0.043,
          0.048,
          0.053,
          0.058,
          0.063,
          0.068
        ]
      }
    },
    "steps": 25
  },
  "thresholds": {
    "offset": 0.07,
    "onset": 0.068
  }
}